qwiic_vl53l1x.py
sparkfun_qwiic_vl53l1x-1.0.1.dist-info/LICENSE
sparkfun_qwiic_vl53l1x-1.0.1.dist-info/METADATA
sparkfun_qwiic_vl53l1x-1.0.1.dist-info/WHEEL
sparkfun_qwiic_vl53l1x-1.0.1.dist-info/top_level.txt
sparkfun_qwiic_vl53l1x-1.0.1.dist-info/RECORD
