Metadata-Version: 2.1
Name: sparkfun-qwiic-vl53l1x
Version: 1.0.1
Summary: SparkFun Electronics Qwiic VL53L1X
Home-page: https://www.sparkfun.com/products/14722
Author: SparkFun Electronics
Author-email: info@sparkfun.com
License: MIT
Keywords: electronics,maker
Platform: UNKNOWN
Classifier: Development Status :: 3 - Alpha
Classifier: Intended Audience :: Developers
Classifier: Topic :: Software Development :: Build Tools
Classifier: License :: OSI Approved :: MIT License
Classifier: Programming Language :: Python :: 2.7
Classifier: Programming Language :: Python :: 3.5
Classifier: Programming Language :: Python :: 3.6
Classifier: Programming Language :: Python :: 3.7
Requires-Dist: sparkfun-qwiic-i2c
